tool_bump_version/__init__.py
tool_bump_version/cli.py
tool_bump_version/main.py
tool_bump_version/py.typed
tool_bump_version-0.1.2.dist-info/METADATA
tool_bump_version-0.1.2.dist-info/WHEEL
tool_bump_version-0.1.2.dist-info/entry_points.txt
tool_bump_version-0.1.2.dist-info/RECORD
